llmp/__init__.py
llmp/components/__init__.py
llmp/components/base.py
llmp/components/evaluation/__init__.py
llmp/components/evaluation/engine.py
llmp/components/evaluation/metrics.py
llmp/components/evaluation/prompts.py
llmp/components/example_manager.py
llmp/components/generator/__init__.py
llmp/components/generator/_prompts.py
llmp/components/generator/concurrent.py
llmp/components/generator/consensus.py
llmp/components/generator/examples.py
llmp/components/generator/simple.py
llmp/components/generator/verification.py
llmp/components/human_verification.py
llmp/components/instruction/__init__.py
llmp/components/instruction/_prompts.py
llmp/components/instruction/generation.py
llmp/components/instruction/mutation.py
llmp/components/instruction/utils.py
llmp/components/job_factory.py
llmp/components/optimizer/__init__.py
llmp/components/optimizer/_prompts.py
llmp/components/optimizer/examples.py
llmp/components/optimizer/instructions.py
llmp/components/optimizer/optimizer.py
llmp/components/settings/__init__.py
llmp/components/settings/global_settings.py
llmp/components/settings/program_settings.py
llmp/components/settings.py
llmp/data/jobs/28b29c66fe9543e9a16aa25a1be22922/event_log.jsonl
llmp/data/jobs/28b29c66fe9543e9a16aa25a1be22922/examples.jsonl
llmp/data/jobs/28b29c66fe9543e9a16aa25a1be22922/generation_log.jsonl
llmp/data/jobs/28b29c66fe9543e9a16aa25a1be22922/metadata.json
llmp/data/jobs/28b29c66fe9543e9a16aa25a1be22922/version_history.jsonl
llmp/data/jobs/ef99861f501942888a73783a6d8202ab/event_log.jsonl
llmp/data/jobs/ef99861f501942888a73783a6d8202ab/examples.jsonl
llmp/data/jobs/ef99861f501942888a73783a6d8202ab/generation_log.jsonl
llmp/data/jobs/ef99861f501942888a73783a6d8202ab/metadata.json
llmp/data/jobs/ef99861f501942888a73783a6d8202ab/version_history.jsonl
llmp/data/jobs/fbe99910ff1f4f4e8e87940c72980ddc/event_log.jsonl
llmp/data/jobs/fbe99910ff1f4f4e8e87940c72980ddc/examples.jsonl
llmp/data/jobs/fbe99910ff1f4f4e8e87940c72980ddc/generation_log.jsonl
pyllmp-0.0.14.dist-info/LICENSE
pyllmp-0.0.14.dist-info/METADATA
pyllmp-0.0.14.dist-info/WHEEL
pyllmp-0.0.14.dist-info/RECORD
