Metadata-Version: 2.1
Name: pyllmp
Version: 0.0.14
Summary: large language model Programming - Type safe structured generation
Home-page: https://github.com/elokus/LLMP
License: MIT
Author: elokow
Author-email: lukas.kowejsza@gmail.com
Requires-Python: >=3.8, !=2.7.*, !=3.0.*, !=3.1.*, !=3.2.*, !=3.3.*, !=3.4.*, !=3.5.*, !=3.6.*, !=3.7.*
Classifier: License :: OSI Approved :: MIT License
Classifier: Programming Language :: Python :: 3
Classifier: Programming Language :: Python :: 3.9
Classifier: Programming Language :: Python :: 3.10
Classifier: Programming Language :: Python :: 3.11
Requires-Dist: colorama (==0.4.6)
Requires-Dist: jsonlines (==4.0.0)
Requires-Dist: jupyter (>=1.0.0,<2.0.0)
Requires-Dist: pydantic (>=1,<3)
Requires-Dist: python-dotenv (>=1)
Requires-Dist: pyyaml (>=5.3,<7.0)
Requires-Dist: structgenie (>=0.1.21)
Requires-Dist: tiktoken (>=0.3,<1.0)
Requires-Dist: tqdm (>=4.62.3,<5.0.0)
Requires-Dist: uuid (>=1.30,<2.0)
Project-URL: Repository, https://github.com/elokus/LLMP
